gio_pyio/__init__.py
gio_pyio-0.0.6.dist-info/LICENSE
gio_pyio-0.0.6.dist-info/METADATA
gio_pyio-0.0.6.dist-info/WHEEL
gio_pyio-0.0.6.dist-info/top_level.txt
gio_pyio-0.0.6.dist-info/RECORD
