Metadata-Version: 2.1
Name: gio-pyio
Version: 0.0.6
Summary: Python like IO for gio
Author-email: Christoph Matthias Kohnen <mail@cmkohnen.de>
Project-URL: Repository, https://github.com/cmkohnen/gio_pyio
Project-URL: Issues, https://github.com/cmkohnen/gio_pyio/issues
Project-URL: Documentation, https://gio-pyio.readthedocs.io
Classifier: Programming Language :: Python :: 3
Classifier: License :: OSI Approved :: GNU General Public License v3 (GPLv3)
Classifier: Operating System :: OS Independent
Requires-Python: >=3.8
License-File: LICENSE
Requires-Dist: PyGObject>=3.42.2
